libcar/__init__.py
libcar/attr.py
libcar/bom.py
libcar/car.py
libcar/facet.py
libcar/keys.py
libcar/rendition.py
libCAR-1.0.0.dist-info/LICENSE
libCAR-1.0.0.dist-info/METADATA
libCAR-1.0.0.dist-info/WHEEL
libCAR-1.0.0.dist-info/top_level.txt
libCAR-1.0.0.dist-info/RECORD
